.gitignore
HACKING.txt
MANIFEST.in
NEWS.txt
README.rst
bootstrap.py
buildout.cfg
setup.py
src/modulus11/__init__.py
src/modulus11/mod11.py
src/modulus11.egg-info/PKG-INFO
src/modulus11.egg-info/SOURCES.txt
src/modulus11.egg-info/dependency_links.txt
src/modulus11.egg-info/entry_points.txt
src/modulus11.egg-info/not-zip-safe
src/modulus11.egg-info/top_level.txt