Metadata-Version: 1.0
Name: modulus11
Version: 0.1
Summary: Compute modulus 11 check digit for TNT consignements tracking number
Home-page: UNKNOWN
Author: Petr Dlouhý
Author-email: petr.dlouhy@email.cz
License: GPL
Platform: UNKNOWN
